polygonation/__init__.py
polygonation/_core.py
polygonation/_version.py
polygonation/tests/__init__.py
polygonation/tests/test_isconvex.py
polygonation/tests/test_polygonate.py
polygonation-0.2.0.dist-info/AUTHORS.rst
polygonation-0.2.0.dist-info/LICENSE
polygonation-0.2.0.dist-info/METADATA
polygonation-0.2.0.dist-info/WHEEL
polygonation-0.2.0.dist-info/entry_points.txt
polygonation-0.2.0.dist-info/top_level.txt
polygonation-0.2.0.dist-info/RECORD
