Metadata-Version: 2.1
Name: polygonation
Version: 0.2.0
Summary: Python package to tessellate a set of points in the plane with polygons.
Home-page: https://github.com/rwijtvliet/polygonation
Author: rwijtvliet
Author-email: rwijtvliet@gmail.com
License: BSD (3-clause)
Platform: UNKNOWN
Classifier: Development Status :: 2 - Pre-Alpha
Classifier: Natural Language :: English
Classifier: Programming Language :: Python :: 3
Requires-Python: >=3.7
Requires-Dist: numpy
Requires-Dist: scipy
